{
  "document": "cpcb_ec_guidelines_industries_2017.pdf",
  "category": "penalties",
  "total_pages": 95,
  "structure": [
    {
      "page": 1,
      "keywords": [
        "There is no text provided to extract policy keywords from. Please provide the text",
        "and I will extract the keywords for you."
      ],
      "preview": "## Page 1  1...",
      "chunks_count": 1
    },
    {
      "page": 2,
      "keywords": [
        "compliance",
        "report",
        "NGT",
        "matter",
        "environmental",
        "pollution",
        "policy."
      ],
      "preview": "## Page 2  2          Compliance Report in the Hon\u2019ble NGT matter of OA No. 593/2017  (Paryavaran Suraksha Samiti and Anr. v/s Union of India & Ors.),  order dated 28th August, 2019                            CENTRAL POLLUTION CONTROL BOARD  \u201cParives...",
      "chunks_count": 1
    },
    {
      "page": 3,
      "keywords": [
        "NGT",
        "ETPs",
        "CETPs",
        "STPs",
        "MSW",
        "Legacy Waste",
        "Compliance Status"
      ],
      "preview": "## Page 3  3    Contents    1.0 Background ........................................................................................................ 4  2.0 Compliance Status of ETPs/CETPs/STPs reported by SPCBs/PCCs ............... 5  3.0  Action take...",
      "chunks_count": 1
    },
    {
      "page": 4,
      "keywords": [
        "ETPs",
        "ETPs/CETPs/STPs",
        "GRAP",
        "MSW",
        "CPCB",
        "CETP",
        "SPCBs/PCCs",
        "NGT",
        "legacy waste dump sites"
      ],
      "preview": "## Page 4  4    1.0 Background  The last hearing by the Hon\u2019ble NGT in the matter of OA No. 593/2017 (Paryavaran  Suraksha Samiti and Anr. v/s Union of India & Ors.) was held on 28.08.2019. The  Hon\u2019ble Tribunal discussed following two reports, submi...",
      "chunks_count": 1
    },
    {
      "page": 5,
      "keywords": [
        "environment restoration",
        "compensation",
        "CPCB (Central Pollution Control Board)",
        "ETPs (Effluent Treatment Plants)",
        "CETPs (Common Effluent Treatment Plants)",
        "STPs (Sewage Treatment Plants)",
        "MSW (Municipal Solid Waste)",
        "water quality management"
      ],
      "preview": "## Page 5  5    default to pay compensation which is to be recovered by the States/UTs, with  effect from 01.04.2020. In default of such collection, the States/UTs are liable  to pay such compensation. The CPCB is to collect the same and utilize for...",
      "chunks_count": 1
    },
    {
      "page": 6,
      "keywords": [
        "CETPs",
        "STPs",
        "environmental standards",
        "closure directions",
        "show-cause notices",
        "legal cases",
        "non-compliance",
        "environmental compliance."
      ],
      "preview": "## Page 6  6      ii. As per the data received from SPCBs/PCCs, there are total 191 CETPs, out of  which 128 CETPs are complying with environmental standards and 63 CETPs are  non-complying. Show-cause notices and closure directions have been issued...",
      "chunks_count": 1
    },
    {
      "page": 7,
      "keywords": [
        "Compliance",
        "directions",
        "pollution control",
        "policy makers",
        "abatement",
        "treatment",
        "interventions",
        "regulators",
        "pollution",
        "control measures."
      ],
      "preview": "## Page 7  7    3.0 Action taken by CPCB for compliance of Hon\u2019ble NGT directions dated  28.08.2019:  i.  River basin wise macro picture of ETPs, CETPs, STPs, MSW  facilities, Legacy Waste sites:  The issue was deliberated in the meetings of the Moni...",
      "chunks_count": 1
    },
    {
      "page": 8,
      "keywords": [
        "non-complying",
        "CTEPs",
        "CETPs",
        "SPCBs",
        "directions",
        "Air and Water Act",
        "Hon'ble",
        "NGT"
      ],
      "preview": "## Page 8  8    2(c).  Barak etc.(Upto Border)     3. Godavari  4. Krishna  5. Cauvery  6. Pennar  7. East flowing rivers between Krishna and Pennar and between  Mahanadi and Godavari  8. East flowing rivers between Krishna and Kanyakumari  9. Mahana...",
      "chunks_count": 1
    },
    {
      "page": 9,
      "keywords": [
        "CETPs",
        "SPCBs",
        "CPCB",
        "OCEMS",
        "environmental compensation",
        "pollution index"
      ],
      "preview": "## Page 9  9    2. SPCBs shall direct all non-complying CETPs to take action as  per the recommendations of CPCB, within a time frame.   3. In case of non-complying CETPs, action as deemed fit including  levying of environmental compensation may be t...",
      "chunks_count": 1
    },
    {
      "page": 10,
      "keywords": [
        "EC",
        "CETPs",
        "NGT",
        "CPCB",
        "ETPs",
        "STPs",
        "SPCCs",
        "Compliance"
      ],
      "preview": "## Page 10  10    Presently, considering the PI value as 80, the same formula is being  used for levying EC on non-complying CETPs. Further, as per the  Hon\u2019ble NGT directions CPCB is in the process of revising EC regime  for non-complying CETPs. The...",
      "chunks_count": 1
    },
    {
      "page": 11,
      "keywords": [
        "It seems there's not enough information. Could you please provide the text you'd like me to extract policy keywords from? I'll return a comma-separated list of 5-8 specific policy keywords once I have the text."
      ],
      "preview": "## Page 11  11...",
      "chunks_count": 1
    },
    {
      "page": 12,
      "keywords": [
        "It appears there is no text given for me to extract policy keywords from. If you could provide the text",
        "I would be happy to assist with extracting policy keywords."
      ],
      "preview": "## Page 12  12...",
      "chunks_count": 1
    },
    {
      "page": 13,
      "keywords": [
        "I couldn't find any text provided. If you provide the text",
        "I can help you extract the specific policy keywords from it."
      ],
      "preview": "## Page 13  13...",
      "chunks_count": 1
    },
    {
      "page": 14,
      "keywords": [
        "It appears there is insufficient information provided to extract specific policy keywords. Can you please provide the relevant text for me to extract the policy keywords? I will then return a comma-separated list of the extracted keywords."
      ],
      "preview": "## Page 14  14...",
      "chunks_count": 1
    },
    {
      "page": 15,
      "keywords": [
        "It seems there's no text provided to extract policy keywords from. Could you please provide the text",
        "and I will do my best to assist you?"
      ],
      "preview": "## Page 15  15...",
      "chunks_count": 1
    },
    {
      "page": 16,
      "keywords": [
        "It appears there is no text on page 16. Please provide the text for me to extract the policy keywords."
      ],
      "preview": "## Page 16  16...",
      "chunks_count": 1
    },
    {
      "page": 17,
      "keywords": [
        "It seems there is no text provided. Please provide the text you would like me to extract policy keywords from",
        "and I will return the list as requested."
      ],
      "preview": "## Page 17  17...",
      "chunks_count": 1
    },
    {
      "page": 18,
      "keywords": [
        "It seems like you didn't provide the text for me to extract policy keywords from. Please provide the text so I can assist you better."
      ],
      "preview": "## Page 18  18...",
      "chunks_count": 1
    },
    {
      "page": 19,
      "keywords": [
        "Unfortunately",
        "I don't see any text in the snippet you provided. Could you please paste the text",
        "and I'll be happy to extract the specific policy keywords for you?"
      ],
      "preview": "## Page 19  19...",
      "chunks_count": 1
    },
    {
      "page": 20,
      "keywords": [
        "It seems there is not enough information to extract policy keywords."
      ],
      "preview": "## Page 20  20...",
      "chunks_count": 1
    },
    {
      "page": 21,
      "keywords": [
        "Unfortunately",
        "it seems there is not enough text to extract any policy keywords. Can you please provide the text so I can assist you with extracting the relevant keywords? I will return a comma-separated list of 5-8 specific policy keywords found in the text."
      ],
      "preview": "## Page 21  21...",
      "chunks_count": 1
    },
    {
      "page": 22,
      "keywords": [
        "It seems there is no text provided. Can you please provide the text so I can extract the policy keywords for you?"
      ],
      "preview": "## Page 22  22...",
      "chunks_count": 1
    },
    {
      "page": 23,
      "keywords": [
        "You haven't provided any text for me to extract policy keywords from. Please provide the text",
        "and I will do my best to assist you."
      ],
      "preview": "## Page 23  23...",
      "chunks_count": 1
    },
    {
      "page": 24,
      "keywords": [
        "It seems there is no text provided. I need the text from which to extract policy keywords."
      ],
      "preview": "## Page 24  24...",
      "chunks_count": 1
    },
    {
      "page": 25,
      "keywords": [
        "There's no text provided",
        "so I cannot extract any keywords from it. If you provide the text",
        "I'd be happy to help."
      ],
      "preview": "## Page 25  25...",
      "chunks_count": 1
    },
    {
      "page": 26,
      "keywords": [
        "It appears there is no text provided for me to extract policy keywords from. Please provide the text and I'd be happy to assist."
      ],
      "preview": "## Page 26  26...",
      "chunks_count": 1
    },
    {
      "page": 27,
      "keywords": [
        "Unfortunately",
        "you haven't provided a text for me to extract policy keywords from. If you provide the text",
        "I'll be happy to help you extract 5-8 specific policy keywords in a comma-separated list."
      ],
      "preview": "## Page 27  27...",
      "chunks_count": 1
    },
    {
      "page": 28,
      "keywords": [
        "Unfortunately",
        "I don't see any text in your prompt to extract policy keywords from. Please provide the text",
        "and I'll do my best to extract 5-8 policy keywords from it."
      ],
      "preview": "## Page 28  28...",
      "chunks_count": 1
    },
    {
      "page": 29,
      "keywords": [
        "You didn't provide the text for me to extract the policy keywords from. Please provide the text",
        "and I'll be happy to assist you with extracting 5-8 specific policy keywords in a comma-separated list."
      ],
      "preview": "## Page 29  29...",
      "chunks_count": 1
    },
    {
      "page": 30,
      "keywords": [
        "Unfortunately",
        "I don't see any text in the space provided. Please provide the text so I can extract the policy keywords for you.\n\nOnce you provide the text",
        "I will be happy to assist you."
      ],
      "preview": "## Page 30  30...",
      "chunks_count": 1
    },
    {
      "page": 31,
      "keywords": [
        "There's no text provided. Please provide the text so I can help you extract the policy keywords."
      ],
      "preview": "## Page 31  31...",
      "chunks_count": 1
    },
    {
      "page": 32,
      "keywords": [
        "It seems there is no text provided. Could you please provide the text so I can extract the policy keywords?"
      ],
      "preview": "## Page 32  32...",
      "chunks_count": 1
    },
    {
      "page": 33,
      "keywords": [
        "It seems there is not enough text to extract policy keywords. Can you provide the text you'd like me to extract from?"
      ],
      "preview": "## Page 33  33...",
      "chunks_count": 1
    },
    {
      "page": 34,
      "keywords": [
        "Unfortunately",
        "the provided text is just a page number and doesn't contain any information to extract policy keywords from. If you could provide the actual text",
        "I would be happy to assist you."
      ],
      "preview": "## Page 34  34...",
      "chunks_count": 1
    },
    {
      "page": 35,
      "keywords": [
        "I don't see any text provided. Please provide the text",
        "and I will extract the specific policy keywords for you."
      ],
      "preview": "## Page 35  35...",
      "chunks_count": 1
    },
    {
      "page": 36,
      "keywords": [
        "There is no provided text to extract policy keywords from. Please provide the relevant text so I can assist you with that. I'll return a list of specific policy keywords as a comma-separated list."
      ],
      "preview": "## Page 36  36...",
      "chunks_count": 1
    },
    {
      "page": 37,
      "keywords": [
        "There is no text to extract policy keywords from. Please provide the text",
        "and I will assist you in extracting 5-8 specific policy keywords."
      ],
      "preview": "## Page 37  37...",
      "chunks_count": 1
    },
    {
      "page": 38,
      "keywords": [
        "It seems there is no provided text to extract policy keywords from. Please provide the text so I can assist you in extracting the necessary information."
      ],
      "preview": "## Page 38  38...",
      "chunks_count": 1
    },
    {
      "page": 39,
      "keywords": [
        "Unfortunately",
        "you provided a page number without any accompanying text. Please provide the necessary text for me to extract the policy keywords."
      ],
      "preview": "## Page 39  39...",
      "chunks_count": 1
    },
    {
      "page": 40,
      "keywords": [
        "It appears there's not enough information to extract policy keywords. Can you provide the text you'd like me to extract the policy keywords from?"
      ],
      "preview": "## Page 40  40...",
      "chunks_count": 1
    },
    {
      "page": 41,
      "keywords": [
        "Extended Content",
        "Page 41",
        "41"
      ],
      "preview": "## Page 41  41...",
      "chunks_count": 1
    },
    {
      "page": 42,
      "keywords": [
        "Extended Content",
        "Page 42",
        "42"
      ],
      "preview": "## Page 42  42...",
      "chunks_count": 1
    },
    {
      "page": 43,
      "keywords": [
        "Extended Content",
        "Page 43",
        "43"
      ],
      "preview": "## Page 43  43...",
      "chunks_count": 1
    },
    {
      "page": 44,
      "keywords": [
        "Extended Content",
        "Page 44",
        "44"
      ],
      "preview": "## Page 44  44...",
      "chunks_count": 1
    },
    {
      "page": 45,
      "keywords": [
        "Extended Content",
        "Page 45",
        "45"
      ],
      "preview": "## Page 45  45...",
      "chunks_count": 1
    },
    {
      "page": 46,
      "keywords": [
        "Extended Content",
        "Page 46",
        "46"
      ],
      "preview": "## Page 46  46...",
      "chunks_count": 1
    },
    {
      "page": 47,
      "keywords": [
        "Extended Content",
        "Page 47",
        "47"
      ],
      "preview": "## Page 47  47...",
      "chunks_count": 1
    },
    {
      "page": 48,
      "keywords": [
        "Extended Content",
        "Page 48",
        "48"
      ],
      "preview": "## Page 48  48...",
      "chunks_count": 1
    },
    {
      "page": 49,
      "keywords": [
        "Extended Content",
        "Page 49",
        "49"
      ],
      "preview": "## Page 49  49...",
      "chunks_count": 1
    },
    {
      "page": 50,
      "keywords": [
        "Extended Content",
        "Page 50",
        "50"
      ],
      "preview": "## Page 50  50...",
      "chunks_count": 1
    },
    {
      "page": 51,
      "keywords": [
        "Extended Content",
        "Page 51",
        "51"
      ],
      "preview": "## Page 51  51...",
      "chunks_count": 1
    },
    {
      "page": 52,
      "keywords": [
        "Extended Content",
        "Page 52",
        "52"
      ],
      "preview": "## Page 52  52...",
      "chunks_count": 1
    },
    {
      "page": 53,
      "keywords": [
        "Extended Content",
        "Page 53",
        "53"
      ],
      "preview": "## Page 53  53...",
      "chunks_count": 1
    },
    {
      "page": 54,
      "keywords": [
        "Extended Content",
        "Page 54",
        "54"
      ],
      "preview": "## Page 54  54...",
      "chunks_count": 1
    },
    {
      "page": 55,
      "keywords": [
        "Extended Content",
        "Page 55",
        "55"
      ],
      "preview": "## Page 55  55...",
      "chunks_count": 1
    },
    {
      "page": 56,
      "keywords": [
        "Extended Content",
        "Page 56",
        "56"
      ],
      "preview": "## Page 56  56...",
      "chunks_count": 1
    },
    {
      "page": 57,
      "keywords": [
        "Extended Content",
        "Page 57",
        "57"
      ],
      "preview": "## Page 57  57...",
      "chunks_count": 1
    },
    {
      "page": 58,
      "keywords": [
        "Extended Content",
        "Page 58",
        "58"
      ],
      "preview": "## Page 58  58...",
      "chunks_count": 1
    },
    {
      "page": 59,
      "keywords": [
        "Extended Content",
        "Page 59",
        "59"
      ],
      "preview": "## Page 59  59...",
      "chunks_count": 1
    },
    {
      "page": 60,
      "keywords": [
        "Extended Content",
        "Page 60",
        "60"
      ],
      "preview": "## Page 60  60...",
      "chunks_count": 1
    },
    {
      "page": 61,
      "keywords": [
        "Extended Content",
        "Page 61",
        "61"
      ],
      "preview": "## Page 61  61...",
      "chunks_count": 1
    },
    {
      "page": 62,
      "keywords": [
        "Extended Content",
        "Page 62",
        "62"
      ],
      "preview": "## Page 62  62...",
      "chunks_count": 1
    },
    {
      "page": 63,
      "keywords": [
        "Extended Content",
        "Page 63",
        "63"
      ],
      "preview": "## Page 63  63...",
      "chunks_count": 1
    },
    {
      "page": 64,
      "keywords": [
        "Extended Content",
        "Page 64",
        "64"
      ],
      "preview": "## Page 64  64...",
      "chunks_count": 1
    },
    {
      "page": 65,
      "keywords": [
        "Extended Content",
        "Page 65",
        "65"
      ],
      "preview": "## Page 65  65...",
      "chunks_count": 1
    },
    {
      "page": 66,
      "keywords": [
        "Extended Content",
        "Page 66",
        "66"
      ],
      "preview": "## Page 66  66...",
      "chunks_count": 1
    },
    {
      "page": 67,
      "keywords": [
        "Extended Content",
        "Page 67",
        "67"
      ],
      "preview": "## Page 67  67...",
      "chunks_count": 1
    },
    {
      "page": 68,
      "keywords": [
        "Extended Content",
        "Page 68",
        "68"
      ],
      "preview": "## Page 68  68...",
      "chunks_count": 1
    },
    {
      "page": 69,
      "keywords": [
        "Extended Content",
        "Page 69",
        "69"
      ],
      "preview": "## Page 69  69...",
      "chunks_count": 1
    },
    {
      "page": 70,
      "keywords": [
        "Extended Content",
        "Page 70",
        "70"
      ],
      "preview": "## Page 70  70...",
      "chunks_count": 1
    },
    {
      "page": 71,
      "keywords": [
        "Extended Content",
        "Page 71",
        "71"
      ],
      "preview": "## Page 71  71...",
      "chunks_count": 1
    },
    {
      "page": 72,
      "keywords": [
        "Extended Content",
        "Page 72",
        "1",
        "Item No. 02"
      ],
      "preview": "## Page 72    1    Item No. 02                   Court No. 1        BEFORE THE NATIONAL GREEN TRIBUNAL   PRINCIPAL BENCH, NEW DELHI      Original Application No. 593/2017  (arising from W.P. (Civil) No. 375/2012 on the file of the Hon\u2019ble  Supreme Co...",
      "chunks_count": 1
    },
    {
      "page": 73,
      "keywords": [
        "Extended Content",
        "Page 73",
        "2",
        "State Boards/Committees. No polluted matter can be discharged"
      ],
      "preview": "## Page 73    2    State Boards/Committees. No polluted matter can be discharged  into a stream or well or on land, and no industry, operation or  process can be established and no out-let for discharge of sewage  used without consent of the State Bo...",
      "chunks_count": 1
    },
    {
      "page": 74,
      "keywords": [
        "Extended Content",
        "Page 74",
        "3",
        "existent in India. Thereby the deficit in capacity of waste treatment"
      ],
      "preview": "## Page 74    3    existent in India. Thereby the deficit in capacity of waste treatment  is of 62%. There is no data available with regard to generation of  sewage in the rural areas.    4.  We may note that discharge of untreated effluents and sewa...",
      "chunks_count": 3
    },
    {
      "page": 75,
      "keywords": [
        "Extended Content",
        "Page 75",
        "4",
        "5."
      ],
      "preview": "## Page 75    4    5.  All the States and UTs where polluted river stretches exist are  required to constitute River Rejuvenation Committees to prepare  actions plans for restoration (which are to be reviewed by the  highest authority in the States,...",
      "chunks_count": 1
    },
    {
      "page": 76,
      "keywords": [
        "Extended Content",
        "Page 76",
        "5",
        "delay the installation of STPs. For delay of the work, the Chief"
      ],
      "preview": "## Page 76    5    delay the installation of STPs. For delay of the work, the Chief  Secretary must identify the officers responsible and assign  specific responsibilities. Wherever there are violations, adverse  entries in the ACRs must be made in r...",
      "chunks_count": 1
    },
    {
      "page": 77,
      "keywords": [
        "Extended Content",
        "Page 77",
        "6",
        "industrial clusters. We are also informed that the setting"
      ],
      "preview": "## Page 77    6    industrial clusters. We are also informed that the setting  up of a common effluent treatment plant, would  ordinarily take approximately two years (in cases where  the process has yet to be commenced). The reason for the  above pr...",
      "chunks_count": 3
    },
    {
      "page": 78,
      "keywords": [
        "Extended Content",
        "Page 78",
        "7",
        "12. We are of the view that in the manner suggested above,"
      ],
      "preview": "## Page 78    7    12. We are of the view that in the manner suggested above,  the malady of sewer treatment, should also be  dealt with simultaneously. We, therefore, hereby  direct that \u201csewage treatment plants\u201d shall also be set  up and made funct...",
      "chunks_count": 1
    },
    {
      "page": 79,
      "keywords": [
        "Extended Content",
        "Page 79",
        "8",
        "report, the Tribunal, vide orders dated 04.07.2017, 18.09.2017 and"
      ],
      "preview": "## Page 79    8    report, the Tribunal, vide orders dated 04.07.2017, 18.09.2017 and  11.10.2017, sought information about the steps taken by the  SPCBs/PCCs.     9.  Vide order dated 03.08.2018, the matter was reviewed and after  noting that in abs...",
      "chunks_count": 1
    },
    {
      "page": 80,
      "keywords": [
        "Extended Content",
        "Page 80",
        "9",
        "assessment of compensation on account of discharge of untreated"
      ],
      "preview": "## Page 80    9    assessment of compensation on account of discharge of untreated  sewage and dumping of solid waste, loss to ecological services due  to illegal mining, deforestation, after taking inputs from expert  bodies.  The Tribunal also dire...",
      "chunks_count": 1
    },
    {
      "page": 81,
      "keywords": [
        "Extended Content",
        "Page 81",
        "10",
        "environmental standards and 59 CETPs are non-complying. There"
      ],
      "preview": "## Page 81    10    environmental standards and 59 CETPs are non-complying. There  are total 13,709 STPs (Municipal and other than municipal), out of  which, 13,113 STPs are complying with environmental standards  and  637  STPs  are  non-complying...",
      "chunks_count": 1
    },
    {
      "page": 82,
      "keywords": [
        "Extended Content",
        "Page 82",
        "11",
        "treatment plant in place. Therefore, no industry requiring"
      ],
      "preview": "## Page 82    11    treatment plant in place. Therefore, no industry requiring  ETP, shall be allowed to operate without ETP.   1.5.4 EC is not a substitute for taking actions under EP Act,  Water Act or Air Act. In fact, units found polluting should...",
      "chunks_count": 1
    },
    {
      "page": 83,
      "keywords": [
        "Extended Content",
        "Page 83",
        "12",
        "recommended"
      ],
      "preview": "## Page 83    12    recommended  by  the  Committee (Lacs Rs.)  Max. 20000  Max. 10000  Max. 1000  Minimum and Maximum  values of EC (O&M Cost  Component)  recommended  by  the  Committee (Lacs Rs./day)  Min. 2  Max. 20  Min. 1  Max. 10  Min. 0.5  Ma...",
      "chunks_count": 3
    },
    {
      "page": 84,
      "keywords": [
        "Extended Content",
        "Page 84",
        "13",
        "Generation-Installed Capacity) + Marginal Average"
      ],
      "preview": "## Page 84    13    Generation-Installed Capacity) + Marginal Average  Capital Cost for Conveyance Facility x  (Total Generation -Operational Capacity)]+ O&M Cost  Factor x Marginal Average O&M Cost  x (Total Generation- Operational Capacity) x No. o...",
      "chunks_count": 1
    },
    {
      "page": 85,
      "keywords": [
        "Extended Content",
        "Page 85",
        "14",
        "Calculated EC (capital cost"
      ],
      "preview": "## Page 85    14    Calculated EC (capital cost   component for Conveyance   System) in Lacs. Rs.  127372.50  13375.50  10323.00  693.75  Calculated EC (Total capital  cost   component) in Lacs Rs.  157035.00  16193.00  11758.00  693.75  Minimum and...",
      "chunks_count": 1
    },
    {
      "page": 86,
      "keywords": [
        "Extended Content",
        "Page 86",
        "15",
        "day waste disposed as per the Rules) + O&M Cost"
      ],
      "preview": "## Page 86    15    day waste disposed as per the Rules) + O&M Cost  Factor x Marginal Average O&M Cost x (Per day waste  generation-Per day waste disposed as per the Rules) x  Number of days violation took place + Environmental  Externality x N  Whe...",
      "chunks_count": 1
    },
    {
      "page": 87,
      "keywords": [
        "Extended Content",
        "Page 87",
        "16",
        "I"
      ],
      "preview": "## Page 87    16            I V .   E n v i r o n m e n t a l   C ompensation in Case of Illegal Extraction of Ground  Water     4.5 Formula for Environmental Compensation for  illegal extraction of ground water      The committee decided that the fo...",
      "chunks_count": 1
    },
    {
      "page": 88,
      "keywords": [
        "Extended Content",
        "Page 88",
        "17",
        "In case of illegal extraction of ground water, quantity of"
      ],
      "preview": "## Page 88    17    In case of illegal extraction of ground water, quantity of  discharge as per the meter reading or as calculated with  assumptions of yield and time may be used for  calculation of ECGw.   4.6 Environmental Compensation Rate (ECRGw...",
      "chunks_count": 3
    },
    {
      "page": 89,
      "keywords": [
        "Extended Content",
        "Page 89",
        "18",
        "Minimum ECGw=Rs 1,00,000/-"
      ],
      "preview": "## Page 89    18    Minimum ECGw=Rs 1,00,000/-      4.6.3 ECRGw for Mining, Infrastructure and Dewatering  Projects    SI.  No Area Category  Water Consumption (m3/day)  <200  200 to <1000  1000 to <5000 5000 &  b Environmental Compensation Rate (ECR...",
      "chunks_count": 1
    },
    {
      "page": 90,
      "keywords": [
        "Extended Content",
        "Page 90",
        "19",
        "recommendation of SPCB/PCC, if required). SPCB/PCC"
      ],
      "preview": "## Page 90    19    recommendation of SPCB/PCC, if required). SPCB/PCC  may bring the issue of illegal extraction of ground water  in industries in to the notice of CGWA for appropriate  action by CGWA.  \uf0b7  Authorities assigned for levy EC and taking...",
      "chunks_count": 1
    },
    {
      "page": 91,
      "keywords": [
        "Extended Content",
        "Page 91",
        "20",
        "to be answerable. Thus, the source for financial resources for the"
      ],
      "preview": "## Page 91    20    to be answerable. Thus, the source for financial resources for the  STPs, stands finalized under the binding judgment of the Hon\u2019ble  Supreme  Court.  Authorities  and  persons  accountable  are  identified. Rigid implementation h...",
      "chunks_count": 1
    },
    {
      "page": 92,
      "keywords": [
        "Extended Content",
        "Page 92",
        "21",
        "discharged in water bodies. Doing so is a criminal offence under"
      ],
      "preview": "## Page 92    21    discharged in water bodies. Doing so is a criminal offence under  the Water Act and is harmful to the environment and public  health. \u2018Precautionary\u2019 principle of environmental law is to be  enforced. Thus, the mandate of law is t...",
      "chunks_count": 1
    },
    {
      "page": 93,
      "keywords": [
        "Extended Content",
        "Page 93",
        "22",
        "18."
      ],
      "preview": "## Page 93    22    18.  The Committee inspected 127 CETPs in 14 States. Figure of CETP  assumed to be 97 was not correct. 66 CETPs were found to be non- compliant. CPCB directed SPCBs to take following steps:    \u201c1. SPCBs shall direct non-complying...",
      "chunks_count": 1
    },
    {
      "page": 94,
      "keywords": [
        "Extended Content",
        "Page 94",
        "23",
        "(ii)"
      ],
      "preview": "## Page 94    23    (ii)  SPCBs/PCCs may ensure remedial action against non- compliant CETPs or individual industries in terms of not  having ETPs/fully compliant ETPs or operating without  consent or in violation of consent conditions. This may be...",
      "chunks_count": 1
    },
    {
      "page": 95,
      "keywords": [
        "Extended Content",
        "Page 95",
        "24",
        "Adarsh Kumar Goel, CP"
      ],
      "preview": "## Page 95    24      Adarsh Kumar Goel, CP          S.P. Wangdi, JM            K. Ramakrishnan, JM          Dr. Nagin Nanda, EM    August 28, 2019  Original Application No. 593/2017  (W.P.(Civil) No. 375/2012)  DV  95...",
      "chunks_count": 1
    }
  ]
}